xia_scw_mongodb/__init__.py
xia_scw_mongodb/engine.cpython-310-darwin.so
xia_scw_mongodb/mongo.cpython-310-darwin.so
xia_scw_mongodb-0.0.3.dist-info/LICENSE.txt
xia_scw_mongodb-0.0.3.dist-info/METADATA
xia_scw_mongodb-0.0.3.dist-info/WHEEL
xia_scw_mongodb-0.0.3.dist-info/top_level.txt
xia_scw_mongodb-0.0.3.dist-info/RECORD
