Metadata-Version: 2.1
Name: xia-scw-mongodb
Version: 0.0.3
Summary: X-I-A
Home-page: https://develop.x-i-a.com/docs/xia-scw-mongodb/0.0.3/index.html
Author: X-I-A
Author-email: admin@x-i-a.com
License: UNKNOWN
Platform: UNKNOWN
Requires-Python: >=3.9
License-File: LICENSE.txt
Requires-Dist: pymongo
Requires-Dist: requests
Requires-Dist: xia-scw-instance
